[
  {
    "id": "1S%!06ETLFV2",
    "code": "1S%!06ETLFV2",
    "used": false
  },
  {
    "id": "PKGBU7*RF&#@",
    "code": "PKGBU7*RF&#@",
    "used": false
  },
  {
    "id": "2HQWU2^7B7JD",
    "code": "2HQWU2^7B7JD",
    "used": false
  },
  {
    "id": "K^AF$01SAPY8",
    "code": "K^AF$01SAPY8",
    "used": false
  },
  {
    "id": "05@3B#W4I2LO",
    "code": "05@3B#W4I2LO",
    "used": false
  },
  {
    "id": "R%LJ^^P4UCIX",
    "code": "R%LJ^^P4UCIX",
    "used": false
  },
  {
    "id": "SXO1LU%4LBJO",
    "code": "SXO1LU%4LBJO",
    "used": false
  },
  {
    "id": "T733KX*!Q564",
    "code": "T733KX*!Q564",
    "used": false
  },
  {
    "id": "ITZP3OYR8@38",
    "code": "ITZP3OYR8@38",
    "used": false
  },
  {
    "id": "N381FPHGKLA6",
    "code": "N381FPHGKLA6",
    "used": false
  },
  {
    "id": "D3QCV8^&U#FA",
    "code": "D3QCV8^&U#FA",
    "used": false
  },
  {
    "id": "4GL8803T5T4@",
    "code": "4GL8803T5T4@",
    "used": false
  },
  {
    "id": "*8KPWPVNGE35",
    "code": "*8KPWPVNGE35",
    "used": false
  },
  {
    "id": "K&O6I$B8$V1H",
    "code": "K&O6I$B8$V1H",
    "used": false
  },
  {
    "id": "W707PAFC@4@O",
    "code": "W707PAFC@4@O",
    "used": false
  },
  {
    "id": "UTFG!ZZ52YF7",
    "code": "UTFG!ZZ52YF7",
    "used": false
  },
  {
    "id": "^JNP#H0S9VUE",
    "code": "^JNP#H0S9VUE",
    "used": false
  },
  {
    "id": "UE^1L%2MEYBS",
    "code": "UE^1L%2MEYBS",
    "used": false
  },
  {
    "id": "Q&50$KWJ@SJ9",
    "code": "Q&50$KWJ@SJ9",
    "used": false
  },
  {
    "id": "MZZ!2D1RXX&$",
    "code": "MZZ!2D1RXX&$",
    "used": false
  },
  {
    "id": "ICTN4PFZNCM2",
    "code": "ICTN4PFZNCM2",
    "used": false
  },
  {
    "id": "EC3B3DWHI#*6",
    "code": "EC3B3DWHI#*6",
    "used": false
  },
  {
    "id": "1^8NMMA6XWCW",
    "code": "1^8NMMA6XWCW",
    "used": false
  },
  {
    "id": "&$0*W^P@RDSW",
    "code": "&$0*W^P@RDSW",
    "used": false
  },
  {
    "id": "#CB1QNSJ6DHK",
    "code": "#CB1QNSJ6DHK",
    "used": false
  },
  {
    "id": "1@H383V4ICFW",
    "code": "1@H383V4ICFW",
    "used": false
  },
  {
    "id": "6FLTY4*26MPP",
    "code": "6FLTY4*26MPP",
    "used": false
  },
  {
    "id": "#&XR#0XMTC$I",
    "code": "#&XR#0XMTC$I",
    "used": false
  },
  {
    "id": "NE^!F42XJ2L9",
    "code": "NE^!F42XJ2L9",
    "used": false
  },
  {
    "id": "V4E^ASF5CH5$",
    "code": "V4E^ASF5CH5$",
    "used": false
  },
  {
    "id": "V1X&C@9F48#J",
    "code": "V1X&C@9F48#J",
    "used": false
  },
  {
    "id": "$T@T^!E0AKJ0",
    "code": "$T@T^!E0AKJ0",
    "used": false
  },
  {
    "id": "6J&GKF4V&0CF",
    "code": "6J&GKF4V&0CF",
    "used": false
  },
  {
    "id": "OCOCP1*$V7CG",
    "code": "OCOCP1*$V7CG",
    "used": false
  },
  {
    "id": "U66#$DI2HKK!",
    "code": "U66#$DI2HKK!",
    "used": false
  },
  {
    "id": "%AEJ6EEREI*#",
    "code": "%AEJ6EEREI*#",
    "used": false
  },
  {
    "id": "O2K$0T7UPO8S",
    "code": "O2K$0T7UPO8S",
    "used": false
  },
  {
    "id": "QQVRR55K0N0Y",
    "code": "QQVRR55K0N0Y",
    "used": false
  },
  {
    "id": "M&XQHY558F3H",
    "code": "M&XQHY558F3H",
    "used": false
  },
  {
    "id": "UTVJH6FT#Y1@",
    "code": "UTVJH6FT#Y1@",
    "used": false
  },
  {
    "id": "TT6S*B#NQIKH",
    "code": "TT6S*B#NQIKH",
    "used": false
  },
  {
    "id": "BZ234!4N9PWV",
    "code": "BZ234!4N9PWV",
    "used": false
  },
  {
    "id": "@9Q%1JZ2UU&9",
    "code": "@9Q%1JZ2UU&9",
    "used": false
  },
  {
    "id": "3$YUOIR4428H",
    "code": "3$YUOIR4428H",
    "used": false
  },
  {
    "id": "SGWMOC0&19I8",
    "code": "SGWMOC0&19I8",
    "used": false
  },
  {
    "id": "BRT%*II*^OP*",
    "code": "BRT%*II*^OP*",
    "used": false
  },
  {
    "id": "TSCB77X6D^@2",
    "code": "TSCB77X6D^@2",
    "used": false
  },
  {
    "id": "V@GWI*34WRKA",
    "code": "V@GWI*34WRKA",
    "used": false
  },
  {
    "id": "GX66MYG&TO8Z",
    "code": "GX66MYG&TO8Z",
    "used": false
  },
  {
    "id": "5^6$W#EWX2GW",
    "code": "5^6$W#EWX2GW",
    "used": false
  }
]