[
  {
    "id": "&56IOLRGS99^",
    "code": "&56IOLRGS99^",
    "used": false
  },
  {
    "id": "TK%7V177BC5R",
    "code": "TK%7V177BC5R",
    "used": false
  },
  {
    "id": "@88LIBM4IW13",
    "code": "@88LIBM4IW13",
    "used": false
  },
  {
    "id": "UX1E33@VQLI9",
    "code": "UX1E33@VQLI9",
    "used": false
  },
  {
    "id": "*WI7BAVO&UDE",
    "code": "*WI7BAVO&UDE",
    "used": false
  },
  {
    "id": "T0I0ZAHF5!5^",
    "code": "T0I0ZAHF5!5^",
    "used": false
  },
  {
    "id": "9$!1EQ2CZZ4Z",
    "code": "9$!1EQ2CZZ4Z",
    "used": false
  },
  {
    "id": "39!&CFFDMEK0",
    "code": "39!&CFFDMEK0",
    "used": false
  },
  {
    "id": "Z9TPD^SFS2XC",
    "code": "Z9TPD^SFS2XC",
    "used": false
  },
  {
    "id": "6A8UGX%4Y4$D",
    "code": "6A8UGX%4Y4$D",
    "used": false
  },
  {
    "id": "V0$C$*&^G610",
    "code": "V0$C$*&^G610",
    "used": false
  },
  {
    "id": "XRI#LD7D*Y$&",
    "code": "XRI#LD7D*Y$&",
    "used": false
  },
  {
    "id": "SSKC&Q46^VV3",
    "code": "SSKC&Q46^VV3",
    "used": false
  },
  {
    "id": "7RN*CPY3W%R1",
    "code": "7RN*CPY3W%R1",
    "used": false
  },
  {
    "id": "H1O38IZ5FD#B",
    "code": "H1O38IZ5FD#B",
    "used": false
  },
  {
    "id": "FH2J9II&N6A2",
    "code": "FH2J9II&N6A2",
    "used": false
  },
  {
    "id": "*R4N@SPWFH1$",
    "code": "*R4N@SPWFH1$",
    "used": false
  },
  {
    "id": "C*E2ZGMWV3PZ",
    "code": "C*E2ZGMWV3PZ",
    "used": false
  },
  {
    "id": "K0#S*XTI10OG",
    "code": "K0#S*XTI10OG",
    "used": false
  },
  {
    "id": "!XRZ6D1QZEQ5",
    "code": "!XRZ6D1QZEQ5",
    "used": false
  },
  {
    "id": "96@TJD3@*QPA",
    "code": "96@TJD3@*QPA",
    "used": false
  },
  {
    "id": "U8%952#MB9S4",
    "code": "U8%952#MB9S4",
    "used": false
  },
  {
    "id": "8%K0BRCU1KE%",
    "code": "8%K0BRCU1KE%",
    "used": false
  },
  {
    "id": "BF69M2*89R2*",
    "code": "BF69M2*89R2*",
    "used": false
  },
  {
    "id": "I3GJ#ZHP$1T1",
    "code": "I3GJ#ZHP$1T1",
    "used": false
  },
  {
    "id": "RZISA9IG92GT",
    "code": "RZISA9IG92GT",
    "used": false
  },
  {
    "id": "!2FPLFDYRMAF",
    "code": "!2FPLFDYRMAF",
    "used": false
  },
  {
    "id": "Y7^PX^OJ#S4U",
    "code": "Y7^PX^OJ#S4U",
    "used": false
  },
  {
    "id": "S!044E&0X#3#",
    "code": "S!044E&0X#3#",
    "used": false
  },
  {
    "id": "3FE$HD5C834!",
    "code": "3FE$HD5C834!",
    "used": false
  },
  {
    "id": "4HBB$#L$3A@7",
    "code": "4HBB$#L$3A@7",
    "used": false
  },
  {
    "id": "P215A8*A4Y03",
    "code": "P215A8*A4Y03",
    "used": false
  },
  {
    "id": "M&BTNNI2#26#",
    "code": "M&BTNNI2#26#",
    "used": false
  },
  {
    "id": "RE@OQC1ROBCT",
    "code": "RE@OQC1ROBCT",
    "used": false
  },
  {
    "id": "7G$#PFQAG$2L",
    "code": "7G$#PFQAG$2L",
    "used": false
  },
  {
    "id": "&&2D%P#F2&#Q",
    "code": "&&2D%P#F2&#Q",
    "used": false
  },
  {
    "id": "PYO^YTKC45*Q",
    "code": "PYO^YTKC45*Q",
    "used": false
  },
  {
    "id": "HO9*7%%7NQP2",
    "code": "HO9*7%%7NQP2",
    "used": false
  },
  {
    "id": "UADP^FYZCB8W",
    "code": "UADP^FYZCB8W",
    "used": false
  },
  {
    "id": "7TH6&VESO&^4",
    "code": "7TH6&VESO&^4",
    "used": false
  },
  {
    "id": "S*SX^&N198RW",
    "code": "S*SX^&N198RW",
    "used": false
  },
  {
    "id": "0HIVP!N0&Z%4",
    "code": "0HIVP!N0&Z%4",
    "used": false
  },
  {
    "id": "3CIULF5T@Q5I",
    "code": "3CIULF5T@Q5I",
    "used": false
  },
  {
    "id": "@WZQX89#J392",
    "code": "@WZQX89#J392",
    "used": false
  },
  {
    "id": "WT0UDV2D25VV",
    "code": "WT0UDV2D25VV",
    "used": false
  },
  {
    "id": "TA%700P817Y*",
    "code": "TA%700P817Y*",
    "used": false
  },
  {
    "id": "N7CMT#^N$2ZQ",
    "code": "N7CMT#^N$2ZQ",
    "used": false
  },
  {
    "id": "NT#VL7^BR2PO",
    "code": "NT#VL7^BR2PO",
    "used": false
  },
  {
    "id": "^4FIV2S04URU",
    "code": "^4FIV2S04URU",
    "used": false
  },
  {
    "id": "C2$G!WY49H&X",
    "code": "C2$G!WY49H&X",
    "used": false
  }
]