[
  {
    "id": "RAGXGB@UI@GZ",
    "code": "RAGXGB@UI@GZ",
    "used": false
  },
  {
    "id": "TKO37&5E!BHD",
    "code": "TKO37&5E!BHD",
    "used": false
  },
  {
    "id": "W5&TR5V#$3SB",
    "code": "W5&TR5V#$3SB",
    "used": false
  },
  {
    "id": "#63!U8!S@JO^",
    "code": "#63!U8!S@JO^",
    "used": false
  },
  {
    "id": "CANNOVQ5TYS5",
    "code": "CANNOVQ5TYS5",
    "used": false
  },
  {
    "id": "&U%CL$%P*NL&",
    "code": "&U%CL$%P*NL&",
    "used": false
  },
  {
    "id": "KNV@4W6HGGE1",
    "code": "KNV@4W6HGGE1",
    "used": false
  },
  {
    "id": "BQ3^0BM%F1KO",
    "code": "BQ3^0BM%F1KO",
    "used": false
  },
  {
    "id": "I84$@0BVWT^7",
    "code": "I84$@0BVWT^7",
    "used": false
  },
  {
    "id": "DKD%BI8G*YU1",
    "code": "DKD%BI8G*YU1",
    "used": false
  },
  {
    "id": "&#GR6ST54%XY",
    "code": "&#GR6ST54%XY",
    "used": false
  },
  {
    "id": "SA!1K$GM1LSH",
    "code": "SA!1K$GM1LSH",
    "used": false
  },
  {
    "id": "L#^XQTZ55SU5",
    "code": "L#^XQTZ55SU5",
    "used": false
  },
  {
    "id": "F75PUK7@4@##",
    "code": "F75PUK7@4@##",
    "used": false
  },
  {
    "id": "%NZ^DELBW0H4",
    "code": "%NZ^DELBW0H4",
    "used": false
  },
  {
    "id": "AEJZ24T1IZCD",
    "code": "AEJZ24T1IZCD",
    "used": false
  },
  {
    "id": "0D7R0FD@#&R9",
    "code": "0D7R0FD@#&R9",
    "used": false
  },
  {
    "id": "ERXRIICKJ3IN",
    "code": "ERXRIICKJ3IN",
    "used": false
  },
  {
    "id": "ZYJQG$KE4X!U",
    "code": "ZYJQG$KE4X!U",
    "used": false
  },
  {
    "id": "B0U85&LE5J7S",
    "code": "B0U85&LE5J7S",
    "used": false
  },
  {
    "id": "58X1H$UZEKA1",
    "code": "58X1H$UZEKA1",
    "used": false
  },
  {
    "id": "@OLQAGT2**A^",
    "code": "@OLQAGT2**A^",
    "used": false
  },
  {
    "id": "^3TXAKBYE&&N",
    "code": "^3TXAKBYE&&N",
    "used": false
  },
  {
    "id": "I2KA967^M4FD",
    "code": "I2KA967^M4FD",
    "used": false
  },
  {
    "id": "$2IT3PWGC4D2",
    "code": "$2IT3PWGC4D2",
    "used": false
  },
  {
    "id": "HGRB2BES4%SM",
    "code": "HGRB2BES4%SM",
    "used": false
  },
  {
    "id": "QJFQEAACQKY2",
    "code": "QJFQEAACQKY2",
    "used": false
  },
  {
    "id": "PATTNFQVG&LV",
    "code": "PATTNFQVG&LV",
    "used": false
  },
  {
    "id": "FR$P5B70KO1$",
    "code": "FR$P5B70KO1$",
    "used": false
  },
  {
    "id": "OMZ&XSDTV6LA",
    "code": "OMZ&XSDTV6LA",
    "used": false
  },
  {
    "id": "&8CN#CLKA3%@",
    "code": "&8CN#CLKA3%@",
    "used": false
  },
  {
    "id": "HQ@TP98G3!N6",
    "code": "HQ@TP98G3!N6",
    "used": false
  },
  {
    "id": "WY3GA2YI0#O9",
    "code": "WY3GA2YI0#O9",
    "used": false
  },
  {
    "id": "@IYTTN#$VKSA",
    "code": "@IYTTN#$VKSA",
    "used": false
  },
  {
    "id": "5Z!GN$S#C296",
    "code": "5Z!GN$S#C296",
    "used": false
  },
  {
    "id": "30^YN^3JQMU2",
    "code": "30^YN^3JQMU2",
    "used": false
  },
  {
    "id": "15V4*5X%D9PK",
    "code": "15V4*5X%D9PK",
    "used": false
  },
  {
    "id": "IXFLHNPW%MAX",
    "code": "IXFLHNPW%MAX",
    "used": false
  },
  {
    "id": "VDTF&HU6Q1XW",
    "code": "VDTF&HU6Q1XW",
    "used": false
  },
  {
    "id": "FKSCQAM5@K9$",
    "code": "FKSCQAM5@K9$",
    "used": false
  },
  {
    "id": "DZWVCQOQQ%WY",
    "code": "DZWVCQOQQ%WY",
    "used": false
  },
  {
    "id": "IO80YL4J2B%5",
    "code": "IO80YL4J2B%5",
    "used": false
  },
  {
    "id": "4AOXX0IZAJ%Z",
    "code": "4AOXX0IZAJ%Z",
    "used": false
  },
  {
    "id": "0E^YQTP6BN#5",
    "code": "0E^YQTP6BN#5",
    "used": false
  },
  {
    "id": "SB%U$052Y2A5",
    "code": "SB%U$052Y2A5",
    "used": false
  },
  {
    "id": "MI6WN0WXLO7V",
    "code": "MI6WN0WXLO7V",
    "used": false
  },
  {
    "id": "J6&1$8MILLA&",
    "code": "J6&1$8MILLA&",
    "used": false
  },
  {
    "id": "HWU1D2NTVW!R",
    "code": "HWU1D2NTVW!R",
    "used": false
  },
  {
    "id": "24#FBLR2N7X6",
    "code": "24#FBLR2N7X6",
    "used": false
  },
  {
    "id": "6KZ0FPR8NBN^",
    "code": "6KZ0FPR8NBN^",
    "used": false
  }
]