[
  {
    "id": "6RQR9VESGRX9",
    "code": "6RQR9VESGRX9",
    "used": false
  },
  {
    "id": "NKZVX27I#1PB",
    "code": "NKZVX27I#1PB",
    "used": false
  },
  {
    "id": "1ZJYMJDUY@#X",
    "code": "1ZJYMJDUY@#X",
    "used": false
  },
  {
    "id": "Q&WLRQ&1@76U",
    "code": "Q&WLRQ&1@76U",
    "used": false
  },
  {
    "id": "P9*CKX@FMAG&",
    "code": "P9*CKX@FMAG&",
    "used": false
  },
  {
    "id": "UWS90TMQ$FZ2",
    "code": "UWS90TMQ$FZ2",
    "used": false
  },
  {
    "id": "I1FXS2#IF7WM",
    "code": "I1FXS2#IF7WM",
    "used": false
  },
  {
    "id": "N8E31NTTRF&#",
    "code": "N8E31NTTRF&#",
    "used": false
  },
  {
    "id": "NVH&4!Q2$KCS",
    "code": "NVH&4!Q2$KCS",
    "used": false
  },
  {
    "id": "!U1O2Z2531US",
    "code": "!U1O2Z2531US",
    "used": false
  },
  {
    "id": "BKXE$Q#&!!W6",
    "code": "BKXE$Q#&!!W6",
    "used": false
  },
  {
    "id": "R*T8D9K%$6QG",
    "code": "R*T8D9K%$6QG",
    "used": false
  },
  {
    "id": "MH4YS7WZ4^^L",
    "code": "MH4YS7WZ4^^L",
    "used": false
  },
  {
    "id": "3DZAY%AWC10J",
    "code": "3DZAY%AWC10J",
    "used": false
  },
  {
    "id": "2470RRGQUF99",
    "code": "2470RRGQUF99",
    "used": false
  },
  {
    "id": "WR0LT9K5E5XH",
    "code": "WR0LT9K5E5XH",
    "used": false
  },
  {
    "id": "2VCYD16$M1BV",
    "code": "2VCYD16$M1BV",
    "used": false
  },
  {
    "id": "7I!!Q5AVN6A3",
    "code": "7I!!Q5AVN6A3",
    "used": false
  },
  {
    "id": "HJHO%&I^II0Q",
    "code": "HJHO%&I^II0Q",
    "used": false
  },
  {
    "id": "77UV$5WM@0O2",
    "code": "77UV$5WM@0O2",
    "used": false
  },
  {
    "id": "@P$X3!B8QIZC",
    "code": "@P$X3!B8QIZC",
    "used": false
  },
  {
    "id": "CCE#0795TDQN",
    "code": "CCE#0795TDQN",
    "used": false
  },
  {
    "id": "2SZX2TQO%MV0",
    "code": "2SZX2TQO%MV0",
    "used": false
  },
  {
    "id": "W*Z50^OUXD@7",
    "code": "W*Z50^OUXD@7",
    "used": false
  },
  {
    "id": "LD59URUNU8M9",
    "code": "LD59URUNU8M9",
    "used": false
  },
  {
    "id": "^ZZ06HZ$0HSP",
    "code": "^ZZ06HZ$0HSP",
    "used": false
  },
  {
    "id": "009RRPEE$UH2",
    "code": "009RRPEE$UH2",
    "used": false
  },
  {
    "id": "ACTG@9DKZ!^7",
    "code": "ACTG@9DKZ!^7",
    "used": false
  },
  {
    "id": "&%BREKK!CWRF",
    "code": "&%BREKK!CWRF",
    "used": false
  },
  {
    "id": "UGIQELTRPV77",
    "code": "UGIQELTRPV77",
    "used": false
  },
  {
    "id": "5&0ZGAF$6T26",
    "code": "5&0ZGAF$6T26",
    "used": false
  },
  {
    "id": "%%FTMR#RDR17",
    "code": "%%FTMR#RDR17",
    "used": false
  },
  {
    "id": "FHOYKM%^24I0",
    "code": "FHOYKM%^24I0",
    "used": false
  },
  {
    "id": "!$VU3L3LH876",
    "code": "!$VU3L3LH876",
    "used": false
  },
  {
    "id": "&VRT6T!P@W*%",
    "code": "&VRT6T!P@W*%",
    "used": false
  },
  {
    "id": "DQ^YVD%540IL",
    "code": "DQ^YVD%540IL",
    "used": false
  },
  {
    "id": "9SYGZHK57HLY",
    "code": "9SYGZHK57HLY",
    "used": false
  },
  {
    "id": "2VO92@^P6IT%",
    "code": "2VO92@^P6IT%",
    "used": false
  },
  {
    "id": "&%1BRAJE7*82",
    "code": "&%1BRAJE7*82",
    "used": false
  },
  {
    "id": "EY@705#32#!L",
    "code": "EY@705#32#!L",
    "used": false
  },
  {
    "id": "Q$3RI9TG!EC^",
    "code": "Q$3RI9TG!EC^",
    "used": false
  },
  {
    "id": "07IX^4EXVD3O",
    "code": "07IX^4EXVD3O",
    "used": false
  },
  {
    "id": "6B3EQ2W&RL#Q",
    "code": "6B3EQ2W&RL#Q",
    "used": false
  },
  {
    "id": "W5&H!5Q$5*ST",
    "code": "W5&H!5Q$5*ST",
    "used": false
  },
  {
    "id": "7SW2OR04T^$W",
    "code": "7SW2OR04T^$W",
    "used": false
  },
  {
    "id": "!UOPZ7*V29BE",
    "code": "!UOPZ7*V29BE",
    "used": false
  },
  {
    "id": "A!3!19*I!^XF",
    "code": "A!3!19*I!^XF",
    "used": false
  },
  {
    "id": "3!05SGO275ZZ",
    "code": "3!05SGO275ZZ",
    "used": false
  },
  {
    "id": "&^^CR1RZTKZU",
    "code": "&^^CR1RZTKZU",
    "used": false
  },
  {
    "id": "M8A5LFB4WBW!",
    "code": "M8A5LFB4WBW!",
    "used": false
  }
]