[
  {
    "id": "YAJ#HVK@W*SP",
    "code": "YAJ#HVK@W*SP",
    "used": false
  },
  {
    "id": "WPVHDSEG129*",
    "code": "WPVHDSEG129*",
    "used": false
  },
  {
    "id": "7I^J@Q%4B$J!",
    "code": "7I^J@Q%4B$J!",
    "used": false
  },
  {
    "id": "UTMV81U0BR4P",
    "code": "UTMV81U0BR4P",
    "used": false
  },
  {
    "id": "D8Y4&L315Z7E",
    "code": "D8Y4&L315Z7E",
    "used": false
  },
  {
    "id": "GK$H&U0OE0#G",
    "code": "GK$H&U0OE0#G",
    "used": false
  },
  {
    "id": "@%OJ2*GI6FVQ",
    "code": "@%OJ2*GI6FVQ",
    "used": false
  },
  {
    "id": "O2S2$D30K#!E",
    "code": "O2S2$D30K#!E",
    "used": false
  },
  {
    "id": "$37ZVZ!N67KT",
    "code": "$37ZVZ!N67KT",
    "used": false
  },
  {
    "id": "@IC9OE&B2TIW",
    "code": "@IC9OE&B2TIW",
    "used": false
  },
  {
    "id": "JAU2JA895B99",
    "code": "JAU2JA895B99",
    "used": false
  },
  {
    "id": "B!P9A!O45@N0",
    "code": "B!P9A!O45@N0",
    "used": false
  },
  {
    "id": "P2JUN427WP6U",
    "code": "P2JUN427WP6U",
    "used": false
  },
  {
    "id": "P*D972&882WJ",
    "code": "P*D972&882WJ",
    "used": false
  },
  {
    "id": "6JZ2F@@1^CJK",
    "code": "6JZ2F@@1^CJK",
    "used": false
  },
  {
    "id": "ED#V9&@Y!EKF",
    "code": "ED#V9&@Y!EKF",
    "used": false
  },
  {
    "id": "MYB^V7@@PD^H",
    "code": "MYB^V7@@PD^H",
    "used": false
  },
  {
    "id": "H%$2WIT17I3O",
    "code": "H%$2WIT17I3O",
    "used": false
  },
  {
    "id": "I0R3KDN$GAU3",
    "code": "I0R3KDN$GAU3",
    "used": false
  },
  {
    "id": "AE^L3P471EBP",
    "code": "AE^L3P471EBP",
    "used": false
  },
  {
    "id": "RV^#PSKX0NJ2",
    "code": "RV^#PSKX0NJ2",
    "used": false
  },
  {
    "id": "IP0HQIC11B3!",
    "code": "IP0HQIC11B3!",
    "used": false
  },
  {
    "id": "^9M5&I5%YR&3",
    "code": "^9M5&I5%YR&3",
    "used": false
  },
  {
    "id": "GT906G%3A^SZ",
    "code": "GT906G%3A^SZ",
    "used": false
  },
  {
    "id": "BY#ZDJVK85B7",
    "code": "BY#ZDJVK85B7",
    "used": false
  },
  {
    "id": "AFTU3L1V41!V",
    "code": "AFTU3L1V41!V",
    "used": false
  },
  {
    "id": "ORY4N63SJH02",
    "code": "ORY4N63SJH02",
    "used": false
  },
  {
    "id": "45WXMAHLSZS3",
    "code": "45WXMAHLSZS3",
    "used": false
  },
  {
    "id": "P3VUAJ!QQ47D",
    "code": "P3VUAJ!QQ47D",
    "used": false
  },
  {
    "id": "F33826&%2CHF",
    "code": "F33826&%2CHF",
    "used": false
  },
  {
    "id": "D222ZTRGWHJ^",
    "code": "D222ZTRGWHJ^",
    "used": false
  },
  {
    "id": "ST1YXO9!F9CO",
    "code": "ST1YXO9!F9CO",
    "used": false
  },
  {
    "id": "PW5H^G#U^C5@",
    "code": "PW5H^G#U^C5@",
    "used": false
  },
  {
    "id": "W58&79W93@1I",
    "code": "W58&79W93@1I",
    "used": false
  },
  {
    "id": "$JW0V&L36T!H",
    "code": "$JW0V&L36T!H",
    "used": false
  },
  {
    "id": "T1%%%G@0X47W",
    "code": "T1%%%G@0X47W",
    "used": false
  },
  {
    "id": "CNC*L%*9AQW2",
    "code": "CNC*L%*9AQW2",
    "used": false
  },
  {
    "id": "#*DFDS35F16P",
    "code": "#*DFDS35F16P",
    "used": false
  },
  {
    "id": "NDRZ081@I4ON",
    "code": "NDRZ081@I4ON",
    "used": false
  },
  {
    "id": "VGBP5@QY6Q@P",
    "code": "VGBP5@QY6Q@P",
    "used": false
  },
  {
    "id": "D27LQ%UUCPLT",
    "code": "D27LQ%UUCPLT",
    "used": false
  },
  {
    "id": "EJRUD&E@W7@C",
    "code": "EJRUD&E@W7@C",
    "used": false
  },
  {
    "id": "3!HW$9&XFMQH",
    "code": "3!HW$9&XFMQH",
    "used": false
  },
  {
    "id": "5V#!GDAQ5^45",
    "code": "5V#!GDAQ5^45",
    "used": false
  },
  {
    "id": "I!DN1^JES43I",
    "code": "I!DN1^JES43I",
    "used": false
  },
  {
    "id": "FNHRO&TC3320",
    "code": "FNHRO&TC3320",
    "used": false
  },
  {
    "id": "C%9Z6#LC364$",
    "code": "C%9Z6#LC364$",
    "used": false
  },
  {
    "id": "5B02GFHAPVYI",
    "code": "5B02GFHAPVYI",
    "used": false
  },
  {
    "id": "Z33XH29QLUYS",
    "code": "Z33XH29QLUYS",
    "used": false
  },
  {
    "id": "U9834QY@$LR7",
    "code": "U9834QY@$LR7",
    "used": false
  }
]