[
  {
    "id": "0LM3BFE3AK3S",
    "code": "0LM3BFE3AK3S",
    "used": false
  },
  {
    "id": "@1D&%JK28SUQ",
    "code": "@1D&%JK28SUQ",
    "used": false
  },
  {
    "id": "Q33^P0XG*JR!",
    "code": "Q33^P0XG*JR!",
    "used": false
  },
  {
    "id": "7XSFB7*ZQ3QJ",
    "code": "7XSFB7*ZQ3QJ",
    "used": false
  },
  {
    "id": "R6QQFW^KD@PM",
    "code": "R6QQFW^KD@PM",
    "used": false
  },
  {
    "id": "A7EL6LTL%AFH",
    "code": "A7EL6LTL%AFH",
    "used": false
  },
  {
    "id": "OA&KVUJ$U*&5",
    "code": "OA&KVUJ$U*&5",
    "used": false
  },
  {
    "id": "Y*8WR2T60E9L",
    "code": "Y*8WR2T60E9L",
    "used": false
  },
  {
    "id": "ENUE*65J0N4I",
    "code": "ENUE*65J0N4I",
    "used": false
  },
  {
    "id": "C5SVQS4ELHFX",
    "code": "C5SVQS4ELHFX",
    "used": false
  },
  {
    "id": "D^RJSFQ@4WWX",
    "code": "D^RJSFQ@4WWX",
    "used": false
  },
  {
    "id": "6Q@%*J*$Y^DA",
    "code": "6Q@%*J*$Y^DA",
    "used": false
  },
  {
    "id": "YO$2#UF*AI^$",
    "code": "YO$2#UF*AI^$",
    "used": false
  },
  {
    "id": "4AA3W81G&LB8",
    "code": "4AA3W81G&LB8",
    "used": false
  },
  {
    "id": "AC97EBOAGFIT",
    "code": "AC97EBOAGFIT",
    "used": false
  },
  {
    "id": "5%!V0T$N0FGY",
    "code": "5%!V0T$N0FGY",
    "used": false
  },
  {
    "id": "CWC@J6!WJ#S5",
    "code": "CWC@J6!WJ#S5",
    "used": false
  },
  {
    "id": "GX08O7BRMEJ#",
    "code": "GX08O7BRMEJ#",
    "used": false
  },
  {
    "id": "TIAKJ^61BFBX",
    "code": "TIAKJ^61BFBX",
    "used": false
  },
  {
    "id": "NAO7O6XJABTJ",
    "code": "NAO7O6XJABTJ",
    "used": false
  },
  {
    "id": "TRTT#%2@BHLK",
    "code": "TRTT#%2@BHLK",
    "used": false
  },
  {
    "id": "XN0&6Z%1&&SA",
    "code": "XN0&6Z%1&&SA",
    "used": false
  },
  {
    "id": "WY6EW%^1RAJJ",
    "code": "WY6EW%^1RAJJ",
    "used": false
  },
  {
    "id": "R7B9*EFF8S2X",
    "code": "R7B9*EFF8S2X",
    "used": false
  },
  {
    "id": "RJA7#VFYP3Y6",
    "code": "RJA7#VFYP3Y6",
    "used": false
  },
  {
    "id": "^TJUERWAPL36",
    "code": "^TJUERWAPL36",
    "used": false
  },
  {
    "id": "I4P^YN21LV@B",
    "code": "I4P^YN21LV@B",
    "used": false
  },
  {
    "id": "B@@%81BUKNL2",
    "code": "B@@%81BUKNL2",
    "used": false
  },
  {
    "id": "OG5$1JDLHIS0",
    "code": "OG5$1JDLHIS0",
    "used": false
  },
  {
    "id": "*!1&$MVEM#VK",
    "code": "*!1&$MVEM#VK",
    "used": false
  },
  {
    "id": "IC7461LDDDNM",
    "code": "IC7461LDDDNM",
    "used": false
  },
  {
    "id": "RGBJ*7L0ES7S",
    "code": "RGBJ*7L0ES7S",
    "used": false
  },
  {
    "id": "E&F%@O64PJCR",
    "code": "E&F%@O64PJCR",
    "used": false
  },
  {
    "id": "X91LP%YR^V@%",
    "code": "X91LP%YR^V@%",
    "used": false
  },
  {
    "id": "FO%301KI3RF!",
    "code": "FO%301KI3RF!",
    "used": false
  },
  {
    "id": "Q4WJ5TA11FQ!",
    "code": "Q4WJ5TA11FQ!",
    "used": false
  },
  {
    "id": "CWKZ#ZFB8F&A",
    "code": "CWKZ#ZFB8F&A",
    "used": false
  },
  {
    "id": "5XG%4ICY*1RH",
    "code": "5XG%4ICY*1RH",
    "used": false
  },
  {
    "id": "0DEZ6VNJ3DYA",
    "code": "0DEZ6VNJ3DYA",
    "used": false
  },
  {
    "id": "$9O1*Y%RGQM1",
    "code": "$9O1*Y%RGQM1",
    "used": false
  },
  {
    "id": "9V%!7MT3FU46",
    "code": "9V%!7MT3FU46",
    "used": false
  },
  {
    "id": "^7A^W^WJZKRH",
    "code": "^7A^W^WJZKRH",
    "used": false
  },
  {
    "id": "ZW&T&SJ4EER&",
    "code": "ZW&T&SJ4EER&",
    "used": false
  },
  {
    "id": "422LQ6ARL53V",
    "code": "422LQ6ARL53V",
    "used": false
  },
  {
    "id": "9U26HSSR*KVG",
    "code": "9U26HSSR*KVG",
    "used": false
  },
  {
    "id": "VF!15KQ05YGB",
    "code": "VF!15KQ05YGB",
    "used": false
  },
  {
    "id": "6@^S&#M42RT@",
    "code": "6@^S&#M42RT@",
    "used": false
  },
  {
    "id": "H#VBZZD7@9@X",
    "code": "H#VBZZD7@9@X",
    "used": false
  },
  {
    "id": "G!LZ&%7%MQ8Y",
    "code": "G!LZ&%7%MQ8Y",
    "used": false
  },
  {
    "id": "VTBTFB$3OZU!",
    "code": "VTBTFB$3OZU!",
    "used": false
  }
]