[
  {
    "id": "Y&VE!RBNMY2@",
    "code": "Y&VE!RBNMY2@",
    "used": false
  },
  {
    "id": "WN6$PXVYE&DC",
    "code": "WN6$PXVYE&DC",
    "used": false
  },
  {
    "id": "ES#KZCTVHL2C",
    "code": "ES#KZCTVHL2C",
    "used": false
  },
  {
    "id": "AX@2QVVJYL19",
    "code": "AX@2QVVJYL19",
    "used": false
  },
  {
    "id": "IPP%TOJ&3FLM",
    "code": "IPP%TOJ&3FLM",
    "used": false
  },
  {
    "id": "R4YE*A8W9D#2",
    "code": "R4YE*A8W9D#2",
    "used": false
  },
  {
    "id": "^NYJ@7CTPJ&J",
    "code": "^NYJ@7CTPJ&J",
    "used": false
  },
  {
    "id": "1U^P^VAK78Q9",
    "code": "1U^P^VAK78Q9",
    "used": false
  },
  {
    "id": "M^HLD$C4ZW@Q",
    "code": "M^HLD$C4ZW@Q",
    "used": false
  },
  {
    "id": "M!&17Q&ZJT8P",
    "code": "M!&17Q&ZJT8P",
    "used": false
  },
  {
    "id": "E18S*I6&2WSZ",
    "code": "E18S*I6&2WSZ",
    "used": false
  },
  {
    "id": "SV23^T!UMYNO",
    "code": "SV23^T!UMYNO",
    "used": false
  },
  {
    "id": "6^N32ARV3&EC",
    "code": "6^N32ARV3&EC",
    "used": false
  },
  {
    "id": "Y2F*W^QZV$&T",
    "code": "Y2F*W^QZV$&T",
    "used": false
  },
  {
    "id": "!QFSA7T&!409",
    "code": "!QFSA7T&!409",
    "used": false
  },
  {
    "id": "6!F1JDCE9P7E",
    "code": "6!F1JDCE9P7E",
    "used": false
  },
  {
    "id": "BX54ZT86JBFS",
    "code": "BX54ZT86JBFS",
    "used": false
  },
  {
    "id": "&T^&DEBY3!E7",
    "code": "&T^&DEBY3!E7",
    "used": false
  },
  {
    "id": "Y5TKADTJT08J",
    "code": "Y5TKADTJT08J",
    "used": false
  },
  {
    "id": "SG!*AO1HGBPC",
    "code": "SG!*AO1HGBPC",
    "used": false
  },
  {
    "id": "31QR6*C%TIN8",
    "code": "31QR6*C%TIN8",
    "used": false
  },
  {
    "id": "$!%MDIHHSC6Q",
    "code": "$!%MDIHHSC6Q",
    "used": false
  },
  {
    "id": "#QG@#43CIU%D",
    "code": "#QG@#43CIU%D",
    "used": false
  },
  {
    "id": "U&!Z03ZE4FKY",
    "code": "U&!Z03ZE4FKY",
    "used": false
  },
  {
    "id": "#5DCE885BD8C",
    "code": "#5DCE885BD8C",
    "used": false
  },
  {
    "id": "4W13C*P*Y6VY",
    "code": "4W13C*P*Y6VY",
    "used": false
  },
  {
    "id": "!O#WGOFPQ5P9",
    "code": "!O#WGOFPQ5P9",
    "used": false
  },
  {
    "id": "XBYCT68$KUW8",
    "code": "XBYCT68$KUW8",
    "used": false
  },
  {
    "id": "8YDSR$AQE7&Q",
    "code": "8YDSR$AQE7&Q",
    "used": false
  },
  {
    "id": "%KC3RW@8LVZ@",
    "code": "%KC3RW@8LVZ@",
    "used": false
  },
  {
    "id": "F^B!J1S1G90&",
    "code": "F^B!J1S1G90&",
    "used": false
  },
  {
    "id": "%B^M83#^O1KX",
    "code": "%B^M83#^O1KX",
    "used": false
  },
  {
    "id": "T9P65TZ16^BK",
    "code": "T9P65TZ16^BK",
    "used": false
  },
  {
    "id": "!SCQOU18WO08",
    "code": "!SCQOU18WO08",
    "used": false
  },
  {
    "id": "X#E91UEF@&UD",
    "code": "X#E91UEF@&UD",
    "used": false
  },
  {
    "id": "FPL7#^@QUZ5D",
    "code": "FPL7#^@QUZ5D",
    "used": false
  },
  {
    "id": "HU786^KHBI*7",
    "code": "HU786^KHBI*7",
    "used": false
  },
  {
    "id": "XZ%OMP0W!G&3",
    "code": "XZ%OMP0W!G&3",
    "used": false
  },
  {
    "id": "Y74FJ6^7%OK9",
    "code": "Y74FJ6^7%OK9",
    "used": false
  },
  {
    "id": "E6&O9KTW2R*R",
    "code": "E6&O9KTW2R*R",
    "used": false
  },
  {
    "id": "A$DHGB5BI06*",
    "code": "A$DHGB5BI06*",
    "used": false
  },
  {
    "id": "*JQAB@3TEL^F",
    "code": "*JQAB@3TEL^F",
    "used": false
  },
  {
    "id": "0PRAAYNK#NTF",
    "code": "0PRAAYNK#NTF",
    "used": false
  },
  {
    "id": "#M8I&#M!9BB$",
    "code": "#M8I&#M!9BB$",
    "used": false
  },
  {
    "id": "&I5Y%J2JPXHX",
    "code": "&I5Y%J2JPXHX",
    "used": false
  },
  {
    "id": "X&7WT&7N$7YC",
    "code": "X&7WT&7N$7YC",
    "used": false
  },
  {
    "id": "8MTUXKDB%&SJ",
    "code": "8MTUXKDB%&SJ",
    "used": false
  },
  {
    "id": "EQMTPVQOTJX&",
    "code": "EQMTPVQOTJX&",
    "used": false
  },
  {
    "id": "OCT7O1Q3DSC$",
    "code": "OCT7O1Q3DSC$",
    "used": false
  },
  {
    "id": "AVP8OZ4OSPFE",
    "code": "AVP8OZ4OSPFE",
    "used": false
  }
]